evipy/__init__.py
evipy/evipy.py
evipy/model_device.py
evipy/model_device_page.py
evipy/model_device_query.py
evipy/model_user.py
evipy-0.0.9.dist-info/METADATA
evipy-0.0.9.dist-info/WHEEL
evipy-0.0.9.dist-info/RECORD
