Metadata-Version: 2.4
Name: evipy
Version: 0.0.9
Summary: Control eviqo devices (via the cloud) in python. See also eviqo-hacs for a home-assistant connection.
Project-URL: Homepage, https://github.com/zacharyasmith/evipy
Project-URL: Repository, https://github.com/zacharyasmith/evipy
Project-URL: Issues, https://github.com/zacharyasmith/evipy/issues
Project-URL: Discussions, https://github.com/zacharyasmith/evipy/discussions
Project-URL: Changelog, https://github.com/zacharyasmith/evipy/releases
Author-email: Zach <zach@smamily.com>
License: MIT
Keywords: charging,eviqo,iot,monitoring,websocket
Classifier: Development Status :: 3 - Alpha
Classifier: Intended Audience :: Developers
Classifier: License :: OSI Approved :: MIT License
Classifier: Programming Language :: Python :: 3
Classifier: Programming Language :: Python :: 3.12
Classifier: Topic :: Home Automation
Classifier: Topic :: Internet :: WWW/HTTP :: Dynamic Content
Classifier: Topic :: Software Development :: Libraries :: Python Modules
Requires-Python: >=3.12
Requires-Dist: dotenv>=0.9.9
Requires-Dist: httpx>=0.28.1
Requires-Dist: pydantic>=2.12.0
Requires-Dist: pytest>=8.4.2
Requires-Dist: rich>=14.2.0
Requires-Dist: websockets>=15.0.1
